[
  {
    "stock_code": "301308",
    "date": "2026-04-05 08:00:02",
    "title": "160亿！科创板70家企业Q1密集投资 半导体成扩产核心赛道",
    "content": "从上游材料与设备，到中游的芯片制造与测试，不少企业都在加快扩产步伐，以应对下游各个市场的AI化和智能化。",
    "source": "东方财富\n东方财富快讯",
    "category": "量化",
    "impact_level": null,
    "id": "ebd00b95"
  },
  {
    "stock_code": "301308",
    "date": "2026-04-05 08:00:02",
    "title": "160亿！科创板70家企业Q1密集投资 半导体成扩产核心赛道",
    "content": "有相关产业链人士向《科创板日报》记者表示，这轮半导体全产业链的扩产潮，本质上是一场由AI技术革命和全球供应链重构共同引爆的“军备竞赛”。",
    "source": "东方财富\n东方财富快讯",
    "category": "量化",
    "impact_level": null,
    "id": "3330af49"
  },
  {
    "stock_code": "301308",
    "date": "2026-04-05 08:00:02",
    "title": "160亿！科创板70家企业Q1密集投资 半导体成扩产核心赛道",
    "content": "芯片封测方面， 甬矽电子 1月12日公告称，拟使用不超21亿元拟投资新建马来西亚集成电路封装和测试生产基地项目，该项目建设内容主要为系统级封装产品等封装产品，下游应用领域包括AIoT、电源模组等。",
    "source": "东方财富\n东方财富快讯",
    "category": "量化",
    "impact_level": null,
    "id": "4fd912e3"
  },
  {
    "stock_code": "301308",
    "date": "2026-04-05 08:00:02",
    "title": "160亿！科创板70家企业Q1密集投资 半导体成扩产核心赛道",
    "content": "一是该公司计划投资约12.51亿元建设光电通讯半导体芯片和器件研发生产基地二期项目；",
    "source": "东方财富\n东方财富快讯",
    "category": "量化",
    "impact_level": null,
    "id": "8d05b19e"
  },
  {
    "stock_code": "301308",
    "date": "2026-04-05 08:00:02",
    "title": "160亿！科创板70家企业Q1密集投资 半导体成扩产核心赛道",
    "content": "但实际上，不少 通用设备 、 自动化设备 、 新材料 领域的企业，亦均为半导体产业链上游，不少公司在对外投资布局的公告中均提到，受益于AI、智能终端、 物联网 等应用领域市场需求的快速发展，公司拟加快布局步伐。",
    "source": "东方财富\n东方财富快讯",
    "category": "传导",
    "impact_level": null,
    "id": "46d09138"
  },
  {
    "stock_code": "301308",
    "date": "2026-04-05 08:00:02",
    "title": "160亿！科创板70家企业Q1密集投资 半导体成扩产核心赛道",
    "content": "具体来看， 艾森股份 正 向上游关键技术延伸 ，其于1月27日宣布拟斥资20亿元在江苏省南通市经济技术开发区投建集成电路材料华东制造基地项目，建设年产2.3万吨集成电路材料的生产线，产品涵盖半导体用光刻胶及配套树脂、电镀液、高纯试剂等核心品类。",
    "source": "东方财富\n东方财富快讯",
    "category": "量化",
    "impact_level": null,
    "id": "5cf19eed"
  },
  {
    "stock_code": "301308",
    "date": "2026-04-05 02:01",
    "title": "“木头姐”发声 这一赛道被严重低估",
    "content": "具体来看，方舟投资旗下3只交易所交易基金——ARKK、ARKW和ARKF合计清仓超过21.3万股 英伟达 ，价值逾3700万美元。",
    "source": "东方财富网\n东方财富焦点资讯",
    "category": "量化",
    "impact_level": null,
    "id": "2149928f"
  },
  {
    "stock_code": "301308",
    "date": "2026-04-03 18:19",
    "title": "国产上市IC企业排名 豪威车载芯片登顶全球第一",
    "content": "最新机构统计的国内上市IC企业综合排名出炉，豪威集团高居榜首，海光信息、江波龙紧随其后。",
    "source": "新浪财经\n新浪个股资讯",
    "category": "事实",
    "impact_level": null,
    "id": "82f163cf"
  },
  {
    "stock_code": "301308",
    "date": "2026-04-03 18:19",
    "title": "国产上市IC企业排名 豪威车载芯片登顶全球第一",
    "content": "从订单来看，海光的增长已经进入兑现期：阿里锁定了28亿元的DCU订单，工行30亿元服务器采购项目中海光CPU是核心算力，电信移动的服务器集采里海光占比超过60%。",
    "source": "新浪财经\n新浪个股资讯",
    "category": "量化",
    "impact_level": null,
    "id": "2126ac1c"
  },
  {
    "stock_code": "301308",
    "date": "2026-04-03 18:19",
    "title": "国产上市IC企业排名 豪威车载芯片登顶全球第一",
    "content": "英伟达2025年营收超过1.5万亿元人民币，而第一名豪威只有不到300亿元，这个差距是客观存在的。",
    "source": "新浪财经\n新浪个股资讯",
    "category": "量化",
    "impact_level": null,
    "id": "6ba58e36"
  },
  {
    "stock_code": "301308",
    "date": "2026-04-03 17:30",
    "title": "深圳上市公司“稳”从何来？",
    "content": "江波龙的财报还未正式披露，其公布的业绩预告显示，2025年将实现净利润12.5亿元至15.5亿元，同比增长150.66%至210.82%。",
    "source": "新浪财经\n新浪个股资讯",
    "category": "量化",
    "impact_level": null,
    "id": "03e3754d"
  },
  {
    "stock_code": "301308",
    "date": "2026-04-03 17:30",
    "title": "深圳上市公司“稳”从何来？",
    "content": "随着存储行业进入上行周期，作为A股存储模组龙头的江波龙获得了多家券商机构的积极关注，“短期受益于存储涨价，长期则依托企业级存储国产替代及自研主控技术构建高壁垒”，基于产业逻辑与自主创新，这家深企驶入发展快速路。",
    "source": "新浪财经\n新浪个股资讯",
    "category": "传导",
    "impact_level": null,
    "id": "35fb5fcb"
  },
  {
    "stock_code": "301308",
    "date": "2026-04-03 17:30",
    "title": "深圳上市公司“稳”从何来？",
    "content": "按照最新总市值排名，深圳超千亿元的企业共有18家，其中电子行业占据最多数，分别是 工业富联 、 立讯精密 、 深南电路 、 江波龙 和 鹏鼎控股 。",
    "source": "新浪财经\n新浪个股资讯",
    "category": "量化",
    "impact_level": null,
    "id": "9be5a19c"
  },
  {
    "stock_code": "301308",
    "date": "2026-04-03 17:30",
    "title": "深圳上市公司“稳”从何来？",
    "content": "登陆创业板仅3年的江波龙，也借助资本市场快速步入头部梯队。",
    "source": "新浪财经\n新浪个股资讯",
    "category": "量化",
    "impact_level": null,
    "id": "a3f261cc"
  },
  {
    "stock_code": "301308",
    "date": "2026-04-02 23:22",
    "title": "江波龙：投资者赞董秘，董秘称回复与公告无关并将做好市值管理",
    "content": "从您回复的信息来看，贵公司的生产经营符合行业的高景气度，虽然您没有公布业绩预告，但也是一个在二级市场极为经典的市值管理动作！",
    "source": "新浪财经\n新浪个股资讯",
    "category": "量化",
    "impact_level": null,
    "id": "3f92a097"
  },
  {
    "stock_code": "301308",
    "date": "2026-04-02 17:00",
    "title": "出海日报 | 中策橡胶10.4亿投建越南轮胎厂，恒瑞探索中国创新药出海新范式",
    "content": "深圳市江波龙电子股份有限公司公告称，通过全资子公司Lexar Europe B.V.购买控股子公司Zilia Eletrônicos剩余19%股权的交易于2026年3月31日完成交割。",
    "source": "新浪财经\n新浪个股资讯",
    "category": "量化",
    "impact_level": null,
    "id": "e6709973"
  },
  {
    "stock_code": "301308",
    "date": "2026-04-02 17:00",
    "title": "出海日报 | 中策橡胶10.4亿投建越南轮胎厂，恒瑞探索中国创新药出海新范式",
    "content": "江波龙拿下境外子公司全部股权",
    "source": "新浪财经\n新浪个股资讯",
    "category": "事实",
    "impact_level": null,
    "id": "68d5247e"
  },
  {
    "stock_code": "301308",
    "date": "2026-04-02 10:41",
    "title": "多只美股存储股连涨两日，谷歌“冲击波”后存储个股迎来反弹",
    "content": "今日A股多只存储个股股价开盘飘红，江波龙（301308.SZ）涨0.97%，佰维存储（688525.SH）涨2.95%，兆易创新（603986.SH）涨1.2%，澜起科技（688008.SH）涨1.8%，香农芯创（300475.SZ）涨1.94%，随后佰维存储、澜起科技、香农芯创涨幅缩分别窄至1.52%、1.38%、0.41%，部分个股转向微跌。",
    "source": "新浪财经\n新浪个股资讯",
    "category": "量化",
    "impact_level": null,
    "id": "50fd6379"
  },
  {
    "stock_code": "301308",
    "date": "2026-04-02 10:41",
    "title": "多只美股存储股连涨两日，谷歌“冲击波”后存储个股迎来反弹\n谷歌“冲击波”后，存储个股反弹",
    "content": "在3月31日江波龙、佰维存储、兆易创新、澜起科技、香农芯创分别跌5.69%、8.62%、6.94%、5.09%、8.37%之后，这几只个股4月1日分别上涨了0.68%、1.7%、7.1%、3.74%、1.95%。",
    "source": "新浪财经\n新浪个股资讯",
    "category": "量化",
    "impact_level": null,
    "id": "eb550387"
  },
  {
    "stock_code": "301308",
    "date": "2026-04-01 21:21",
    "title": "江波龙：公司旗下元成苏州在存储芯片封装测试领域具有领先的产业地位",
    "content": "在自有产能基础上，公司目前已形成全球化产能与国内产能兼顾、自主产能与委外产能并行的制造格局，外部封测企业的合作亦能为公司提供较好的供应链资源补充。",
    "source": "新浪财经\n新浪个股资讯",
    "category": "事实",
    "impact_level": null,
    "id": "3a6e5e22"
  },
  {
    "stock_code": "301308",
    "date": "2026-04-01 21:21",
    "title": "江波龙：公司旗下元成苏州在存储芯片封装测试领域具有领先的产业地位",
    "content": "证券日报网讯 4月1日，江波龙在互动平台回答投资者提问时表示，公司旗下元成苏州在存储芯片封装测试领域具有领先的产业地位，其自主高端封测能力能够较好匹配业务节奏与高价值客户的交付要求。",
    "source": "新浪财经\n新浪个股资讯",
    "category": "量化",
    "impact_level": null,
    "id": "7b013eb3"
  },
  {
    "stock_code": "301308",
    "date": "2026-04-01 20:45",
    "title": "江波龙：看好AI时代端侧应用，自研技术提供产品方案\n江波龙：回应产品量产、流片进展及AI存储方案毛利率等问题",
    "content": "公司看好AI时代下的端侧AI应用场景，在持续多年的自主研发投入下，公司目前所具备的自研芯片能力、固件算法能力、自主封测能力以及产品创新能力，能够为端侧AI的需求提供有价值的、创造性产品。",
    "source": "新浪财经\n新浪个股资讯",
    "category": "量化",
    "impact_level": null,
    "id": "25312905"
  },
  {
    "stock_code": "301308",
    "date": "2026-04-01 20:45",
    "title": "江波龙：回应2026年AI存储业务规划及与传统业务协同问题",
    "content": "请问公司2026年针对AI存储相关业务，规划了多少专项研发投入与产能配套？",
    "source": "新浪财经\n新浪个股资讯",
    "category": "量化",
    "impact_level": null,
    "id": "df7cbafc"
  },
  {
    "stock_code": "301308",
    "date": "2026-04-01 20:45",
    "title": "江波龙：回应2026年AI存储业务规划及与传统业务协同问题",
    "content": "公司2025年度向特定对象发行A股股票的主要募投项目有“面向AI领域的高端存储器研发及产业化项目”及“半导体存储主控芯片系列研发项目”，公司在募集说明书中详细披露了公司围绕AI服务器存储、AI端侧存储、主控芯片等重要研发项目的投入规划，具体内容您可查阅相关公告。",
    "source": "新浪财经\n新浪个股资讯",
    "category": "量化",
    "impact_level": null,
    "id": "993c942a"
  },
  {
    "stock_code": "301308",
    "date": "2026-04-01 20:45",
    "title": "江波龙：看好AI时代端侧应用，自研技术提供产品方案",
    "content": "如何保障相关技术能持续匹配未来端侧AI的算力与存储需求，避免技术快速迭代带来的落后风险￼￼￼？",
    "source": "新浪财经\n新浪个股资讯",
    "category": "事实",
    "impact_level": null,
    "id": "b2a88a8d"
  },
  {
    "stock_code": "301308",
    "date": "2026-04-01 20:45",
    "title": "江波龙：自研技术提供性价比选择，已布局丰富知识产权",
    "content": "董秘您好，公司本次推出的HLC高级缓存、存内无损压缩、MoE专家模块卸载等核心技术，核心价值是用NAND替代部分DRAM实现端侧AI设备降本增效，这与上游存储原厂的核心商业利益存在潜在冲突。",
    "source": "新浪财经\n新浪个股资讯",
    "category": "事实",
    "impact_level": null,
    "id": "30f474df"
  },
  {
    "stock_code": "301308",
    "date": "2026-04-01 20:45",
    "title": "江波龙：首发SPU与iSA，已与部分平台调优但未形成实质收入",
    "content": "公司的相关产品已经与紫光展锐、AMD主芯片平台完成了联合调优，并在进一步的商业化推进当中，目前尚未形成实质性的收入贡献，但在AI大模型端侧落地的产业趋势下，具备广阔的应用前景，公司将持续推进相关业务发展。",
    "source": "新浪财经\n新浪个股资讯",
    "category": "事实",
    "impact_level": null,
    "id": "077c3b33"
  },
  {
    "stock_code": "301308",
    "date": "2026-04-01 20:45",
    "title": "江波龙：看好AI时代端侧应用，自研技术提供产品方案",
    "content": "董秘您好，公司本次发布的方案深度联合了联芸、紫光展锐等国产产业链厂商，请问公司在国产端侧AI存储产业链闭环中的核心定位是什么？",
    "source": "新浪财经\n新浪个股资讯",
    "category": "事实",
    "impact_level": null,
    "id": "4a7d9f76"
  },
  {
    "stock_code": "301308",
    "date": "2026-04-01 20:45",
    "title": "江波龙：回应2026年AI存储业务规划及与传统业务协同问题",
    "content": "董秘您好，本次系列发布标志着公司从传统存储模组供应商，向AI存储全栈解决方案提供商的战略升级。",
    "source": "新浪财经\n新浪个股资讯",
    "category": "事实",
    "impact_level": null,
    "id": "74de367b"
  },
  {
    "stock_code": "301308",
    "date": "2026-04-01 20:45",
    "title": "江波龙：自研技术提供性价比选择，已布局丰富知识产权",
    "content": "公司与上游存储原厂之间保持着深度、长期及良好的合作以及沟通，在市场分工不同的情况下，您关注的潜在冲突并不存在。",
    "source": "新浪财经\n新浪个股资讯",
    "category": "事实",
    "impact_level": null,
    "id": "fbc3e02b"
  },
  {
    "stock_code": "301308",
    "date": "2026-04-01 20:45",
    "title": "江波龙：看好AI时代端侧应用，自研技术提供产品方案",
    "content": "针对端侧大模型快速迭代的行业趋势，公司SPU与iSA技术未来2-3年的迭代路线是怎样的？",
    "source": "新浪财经\n新浪个股资讯",
    "category": "量化",
    "impact_level": null,
    "id": "cd69ebf6"
  },
  {
    "stock_code": "301308",
    "date": "2026-04-01 20:45",
    "title": "江波龙：回应2026年AI存储业务规划及与传统业务协同问题",
    "content": "AI存储业务，与公司现有的各类存储业务共享技术底座，并在不同场景下互相配合，公司有足够的研发能力以及经验，协调好业务的资源投入，依据客户及市场需求，确保各类业务并重发展。",
    "source": "新浪财经\n新浪个股资讯",
    "category": "事实",
    "impact_level": null,
    "id": "f5823109"
  },
  {
    "stock_code": "301308",
    "date": "2026-04-01 20:45",
    "title": "江波龙：回应产品量产、流片进展及AI存储方案毛利率等问题",
    "content": "董秘您好， 本次发布的搭载联芸1802主控的PCIe Gen5 mSSD已公布完整性能参数，请问该产品目前是否已实现量产，是否已拿到明确的客户意向订单？",
    "source": "新浪财经\n新浪个股资讯",
    "category": "事实",
    "impact_level": null,
    "id": "2b50963b"
  },
  {
    "stock_code": "301308",
    "date": "2026-04-01 20:45",
    "title": "江波龙：回应2026年AI存储业务规划及与传统业务协同问题",
    "content": "该业务与公司现有消费级、企业级、车规级存储业务如何形成协同，是否会挤压原有传统业务的资源投入￼￼￼？",
    "source": "新浪财经\n新浪个股资讯",
    "category": "传导",
    "impact_level": null,
    "id": "d8c7ebcb"
  },
  {
    "stock_code": "301308",
    "date": "2026-04-01 20:45",
    "title": "江波龙：看好AI时代端侧应用，自研技术提供产品方案",
    "content": "最后，创新型产品的落地导入正在进行当中，公司亦将持续关注前沿技术的发展。",
    "source": "新浪财经\n新浪个股资讯",
    "category": "事实",
    "impact_level": null,
    "id": "9abc78d0"
  },
  {
    "stock_code": "301308",
    "date": "2026-04-01 20:45",
    "title": "江波龙：自研技术提供性价比选择，已布局丰富知识产权",
    "content": "公司始终高度重视核心技术的自主研发与知识产权保护，目前已在主控芯片设计、固件算法开发、存储器设计、封装测试等关键环节形成了丰富的知识产权布局，并持续完善公司的专利护城河。",
    "source": "新浪财经\n新浪个股资讯",
    "category": "事实",
    "impact_level": null,
    "id": "229e47e9"
  },
  {
    "stock_code": "301308",
    "date": "2026-04-01 20:45",
    "title": "江波龙：首发SPU与iSA，已与部分平台调优但未形成实质收入",
    "content": "董秘您好，请问公司本次首发的SPU存储处理单元与iSA存储智能体，目前已完成哪些主流算力架构（x86/ARM/RISC-V）、操作系统及大模型推理框架的底层适配？",
    "source": "新浪财经\n新浪个股资讯",
    "category": "事实",
    "impact_level": null,
    "id": "9541ff60"
  },
  {
    "stock_code": "301308",
    "date": "2026-04-01 20:45",
    "title": "江波龙：自研技术提供性价比选择，已布局丰富知识产权",
    "content": "请问针对SPU、iSA相关核心技术，公司已布局多少项自主发明专利？",
    "source": "新浪财经\n新浪个股资讯",
    "category": "量化",
    "impact_level": null,
    "id": "e0957945"
  },
  {
    "stock_code": "301308",
    "date": "2026-04-01 20:45",
    "title": "江波龙：回应产品量产、流片进展及AI存储方案毛利率等问题",
    "content": "采用5nm制程的SPU芯片目前流片进展如何？",
    "source": "新浪财经\n新浪个股资讯",
    "category": "事实",
    "impact_level": null,
    "id": "d515a123"
  },
  {
    "stock_code": "301308",
    "date": "2026-04-01 20:45",
    "title": "江波龙：回应产品量产、流片进展及AI存储方案毛利率等问题",
    "content": "最后，创新型产品的落地导入正在进行当中，相关产品与技术创新对于公司业绩的贡献尚需时日，公司将视情况在相关定期报告中统一、公开的向不特定投资者进行披露。",
    "source": "新浪财经\n新浪个股资讯",
    "category": "量化",
    "impact_level": null,
    "id": "4d6e05d9"
  },
  {
    "stock_code": "301308",
    "date": "2026-04-01 20:45",
    "title": "江波龙：首发SPU与iSA，已与部分平台调优但未形成实质收入",
    "content": "是否已进入头部AI PC、AI手机厂商的供应链验证流程，预计何时可实现规模化商用出货？",
    "source": "新浪财经\n新浪个股资讯",
    "category": "影响",
    "impact_level": null,
    "id": "56640299"
  },
  {
    "stock_code": "301308",
    "date": "2026-04-01 20:45",
    "title": "江波龙：回应产品量产、流片进展及AI存储方案毛利率等问题",
    "content": "相关AI存储全栈方案的毛利率，相较于公司传统存储模组业务预计有多大的提升空间？",
    "source": "新浪财经\n新浪个股资讯",
    "category": "影响",
    "impact_level": null,
    "id": "5446aab5"
  },
  {
    "stock_code": "301308",
    "date": "2026-04-01 20:38",
    "title": "关于为子公司提供担保的进展公告",
    "content": "二、对外担保事项进展因香港江波龙日常经营的需要，香港江波龙向TheHongkongandShanghaiBankingCorporationLimited（以下简称“汇丰银行”）申请4,000万美元的银行授信额度，公司为前述授信业务提供连带责任保证，并签署了《GUARANTEE(LimitedAmount)》。",
    "source": "巨潮资讯\n巨潮资讯公告",
    "category": "量化",
    "impact_level": null,
    "id": "e265f5a0"
  },
  {
    "stock_code": "301308",
    "date": "2026-04-01 20:38",
    "title": "关于为子公司提供担保的进展公告",
    "content": "2、债务人：江波龙电子（香港）有限公司3、保证人：深圳市江波龙电子股份有限公司4、保证金额：不超过4,000.00万美元5、保证方式：连带责任保证担保6、保证范围：担保人不可撤销且无条件地保证应银行要求支付担保款项，",
    "source": "巨潮资讯\n巨潮资讯公告",
    "category": "量化",
    "impact_level": null,
    "id": "4809c06d"
  },
  {
    "stock_code": "301308",
    "date": "2026-04-01 20:38",
    "title": "关于为子公司提供担保的进展公告",
    "content": "本次提供担保后，公司为香港江波龙提供的担保余额的具体情况如下表所示：",
    "source": "巨潮资讯\n巨潮资讯公告",
    "category": "事实",
    "impact_level": null,
    "id": "40cd08e0"
  },
  {
    "stock_code": "301308",
    "date": "2026-04-01 20:38",
    "title": "关于为子公司提供担保的进展公告",
    "content": "虽然香港江波龙未提供反担保，但其系公司的全资子公司，公司拥有完全的控制权。",
    "source": "巨潮资讯\n巨潮资讯公告",
    "category": "事实",
    "impact_level": null,
    "id": "3a603411"
  },
  {
    "stock_code": "301308",
    "date": "2026-04-01 20:38",
    "title": "关于为子公司提供担保的进展公告",
    "content": "单位：人民币亿元担保方被担保方担保方持股比例被担保方最近一期资产负债率经审批的预计担保额度担保额度占上市公司最近一期净资产比例是否关联担保公司香港江波龙100%67.60%65.00100.50%否注：表格中所提及最近一期经审计数据系截止至2024年12月31日的经审计数据。",
    "source": "巨潮资讯\n巨潮资讯公告",
    "category": "政策",
    "impact_level": null,
    "id": "eca88540"
  },
  {
    "stock_code": "301308",
    "date": "2026-04-01 20:38",
    "title": "关于为子公司提供担保的进展公告",
    "content": "其中经审议通过的公司为子公司江波龙电子（香港）有限公司（以下简称“香港江波龙”）提供担保额度的具体情况如下：",
    "source": "巨潮资讯\n巨潮资讯公告",
    "category": "事实",
    "impact_level": null,
    "id": "4990ee08"
  },
  {
    "stock_code": "301308",
    "date": "2026-04-01 19:55",
    "title": "3月机构调研最新动向曝光",
    "content": "从调研次数上看， 敷尔佳 、 安培龙 、 光力科技 、 江波龙 等公司3月份接受机构调研的次数居前，其中 敷尔佳 3月份接受机构调研的次数超过10次。",
    "source": "新浪财经\n新浪个股资讯",
    "category": "量化",
    "impact_level": null,
    "id": "edb95730"
  },
  {
    "stock_code": "301308",
    "date": "2026-04-01 19:30",
    "title": "江波龙：公司将于4月28日同步披露2025年年报和2026年一季报\n江波龙：投资者询问财报披露原因，董秘回应进度正常",
    "content": "您提到的对公司职能部门团队加强建设的建议，公司管理层将不时进行相关审视评估，确保公司随时保持满足上市公司监管要求的相应能力，感谢您的关注。",
    "source": "新浪财经\n新浪个股资讯",
    "category": "政策",
    "impact_level": null,
    "id": "89901867"
  },
  {
    "stock_code": "301308",
    "date": "2026-04-01 18:27",
    "title": "江波龙：投资者询问财报披露原因，董秘回应进度正常",
    "content": "董秘您好，公司年报定在4月28日最后截止日发布，一季报也大概率同步或延后披露。",
    "source": "新浪财经\n新浪个股资讯",
    "category": "量化",
    "impact_level": null,
    "id": "ca1c8647"
  },
  {
    "stock_code": "301308",
    "date": "2026-04-01 18:27",
    "title": "江波龙：投资者询问财报披露原因，董秘回应进度正常",
    "content": "还是现有财务、内控团队能力，暂时跟不上公司业务扩张速度？",
    "source": "新浪财经\n新浪个股资讯",
    "category": "事实",
    "impact_level": null,
    "id": "d6319e6c"
  },
  {
    "stock_code": "301308",
    "date": "2026-04-01 18:27",
    "title": "江波龙：投资者询问财报披露原因，董秘回应进度正常",
    "content": "想了解，公司目前打算如何补齐人才与核算管理短板，匹配自身高速发展节奏？",
    "source": "新浪财经\n新浪个股资讯",
    "category": "事实",
    "impact_level": null,
    "id": "09e269f2"
  },
  {
    "stock_code": "301308",
    "date": "2026-04-01 09:48",
    "title": "硬核拆解宇树G1机器人：毛利率超40%，供应链全曝光，护城河在于顶尖运控算法",
    "content": "拆机显示，其核心硬件均为英特尔、大疆、 江波龙 等供应链的成熟器件，硬件本身无高壁垒，真正的护城河在于自研运控算法。",
    "source": "新浪财经\n新浪个股资讯",
    "category": "事实",
    "impact_level": null,
    "id": "4d1bc603"
  },
  {
    "stock_code": "301308",
    "date": "2026-04-01 09:48",
    "title": "硬核拆解宇树G1机器人：毛利率超40%，供应链全曝光，护城河在于顶尖运控算法",
    "content": "分析师写道： G1核心硬件均为行业可采购、可量产的成熟器件，硬件层面无高壁垒（供应链包括英特尔、大疆、 瑞芯微 、佰维、江波龙、强脑科技等公司）；",
    "source": "新浪财经\n新浪个股资讯",
    "category": "事实",
    "impact_level": null,
    "id": "996dfe17"
  },
  {
    "stock_code": "301308",
    "date": "2026-04-01 09:48",
    "title": "硬核拆解宇树G1机器人：毛利率超40%，供应链全曝光，护城河在于顶尖运控算法",
    "content": "EDU版额外搭载Nvidia Jetson Orin NX，提供100TOPS边缘AI算力。",
    "source": "新浪财经\n新浪个股资讯",
    "category": "叙事",
    "impact_level": null,
    "id": "29e0f29d"
  },
  {
    "stock_code": "301308",
    "date": "2026-03-31 22:30",
    "title": "江波龙：公司计划于2026年4月28日披露2025年年度报告及2026年第一季度报告\n江波龙：公司将于4月28日同步披露2025年年报和2026年一季报\n江波龙：本公司自1999年成立以来，一直使用江波龙做为公司商号",
    "content": "以上内容为证券之星据公开信息整理，由AI算法生成（网信算备310104345710301240019号），不构成",
    "source": "新浪财经\n新浪个股资讯",
    "category": "事实",
    "impact_level": null,
    "id": "6d374c50"
  },
  {
    "stock_code": "301308",
    "date": "2026-03-31 22:30",
    "title": "江波龙：公司计划于2026年4月28日披露2025年年度报告及2026年第一季度报告\n江波龙：投资者盼利好，董秘回应业绩预告披露情况",
    "content": "您提到的季度性业绩预告，由于其不属于创业板上市公司强制要求披露范畴，因此，公司将根据法律法规规定，并结合公司情况与市场影响等因素综合考虑。",
    "source": "新浪财经\n新浪个股资讯",
    "category": "事实",
    "impact_level": null,
    "id": "8b436792"
  },
  {
    "stock_code": "301308",
    "date": "2026-03-31 21:31",
    "title": "江波龙：目前存储行业处于高景气周期，绝大部分存储公司均受益于此\n江波龙：公司计划于2026年4月28日披露2025年年度报告及2026年第一季度报告\n江波龙：投资者盼利好，董秘回应业绩预告披露情况",
    "content": "目前存储行业受到需求拉动的影响，处于高景气周期，绝大部分存储公司均受益于此。",
    "source": "新浪财经\n新浪个股资讯",
    "category": "量化",
    "impact_level": null,
    "id": "31651df6"
  },
  {
    "stock_code": "301308",
    "date": "2026-03-31 21:31",
    "title": "江波龙：目前存储行业处于高景气周期，绝大部分存储公司均受益于此\n江波龙：公司计划于2026年4月28日披露2025年年度报告及2026年第一季度报告\n江波龙：投资者盼利好，董秘回应业绩预告披露情况",
    "content": "公司目前生产经营正常，发展趋势符合行业情况。",
    "source": "新浪财经\n新浪个股资讯",
    "category": "事实",
    "impact_level": null,
    "id": "5302462b"
  },
  {
    "stock_code": "301308",
    "date": "2026-03-31 21:21",
    "title": "江波龙：投资者盼利好，董秘回应业绩预告披露情况",
    "content": "董秘您好，一季度已收官，今年一季度行业整体景气度极高，从已提前披露业绩的友商来看，增长态势十分亮眼。",
    "source": "新浪财经\n新浪个股资讯",
    "category": "量化",
    "impact_level": null,
    "id": "c69e5be8"
  },
  {
    "stock_code": "301308",
    "date": "2026-03-31 21:21",
    "title": "江波龙：投资者盼利好，董秘回应业绩预告披露情况",
    "content": "佰维、 德明利 股价相继多次刷新历史新高，而贵司股价仍在低位徘徊，这不仅让个人投资者心生落差，也更期待公司能紧跟行业大势、做好市值管理，实现正向发展。",
    "source": "新浪财经\n新浪个股资讯",
    "category": "量化",
    "impact_level": null,
    "id": "ee8f046a"
  },
  {
    "stock_code": "301308",
    "date": "2026-03-31 21:21",
    "title": "江波龙：投资者盼利好，董秘回应业绩预告披露情况",
    "content": "希望公司后续能迎头赶上，请问一季度财务预告是否有最新进展可以披露？",
    "source": "新浪财经\n新浪个股资讯",
    "category": "事实",
    "impact_level": null,
    "id": "95af35af"
  },
  {
    "stock_code": "301308",
    "date": "2026-03-31 20:16",
    "title": "存储价格突然“跳水”：到底是回调信号，还是短期波动？",
    "content": "比如，为应对存储涨价给下游带来的成本压力， 江波龙 自研了HLC（High Level Cache，高级缓存技术）技术，可以在减少DRAM使用的同时，不影响用户体验。",
    "source": "新浪财经\n新浪个股资讯",
    "category": "事实",
    "impact_level": null,
    "id": "7e2ba851"
  },
  {
    "stock_code": "301308",
    "date": "2026-03-31 20:05",
    "title": "一周亏光半年利润！DDR5内存条价格单条跌去千元，华强北囤货商疯狂抛售\n存储芯片概念持续调整 佰维存储跌近10%\n超3600股下跌",
    "content": "存储芯片概念盘中持续调整，佰维存储跌近10%，德明利、香农芯创、雅克科技、江波龙、普冉股份、兆易创新均跌超5%。",
    "source": "新浪财经\n新浪个股资讯",
    "category": "量化",
    "impact_level": null,
    "id": "4c2919e5"
  },
  {
    "stock_code": "301308",
    "date": "2026-03-31 20:05",
    "title": "一周亏光半年利润！DDR5内存条价格单条跌去千元，华强北囤货商疯狂抛售",
    "content": "隔夜美光暴跌 9.88% ， 3 月 30 日 A 股存储芯片板块应声重挫：存储器指数跌 0.53% ， 佰维存储 跌 2.69% ， 江波龙 跌 1.57% 。",
    "source": "新浪财经\n新浪个股资讯",
    "category": "量化",
    "impact_level": null,
    "id": "818f9ea2"
  },
  {
    "stock_code": "301308",
    "date": "2026-03-31 20:05",
    "title": "一周亏光半年利润！DDR5内存条价格单条跌去千元，华强北囤货商疯狂抛售",
    "content": "3 月 28 日，谷歌发布 TurboQuant 内存压缩算法，宣称能将 AI 推理阶段的 KV Cache 空间需求减少到原来的 1/6 ，同时在英伟达 H100 GPU 上的特定测试中性能提升高达 8 倍。",
    "source": "新浪财经\n新浪个股资讯",
    "category": "量化",
    "impact_level": null,
    "id": "f15bae57"
  },
  {
    "stock_code": "301308",
    "date": "2026-03-31 19:08",
    "title": "江波龙：投资者建议更名，董秘称现有名称利于业务发展\n江波龙：本公司自1999年成立以来，一直使用江波龙做为公司商号",
    "content": "本公司自1999年成立以来，一直使用江波龙做为公司商号，在业内拥有很高的知名度和辨识度，公司名称的稳定有利于保持公司的形象和业务连续性，也是公司对客户，供应商和产业其他各类合作伙伴社会责任的体现，这些均能助力公司业绩稳步提升。",
    "source": "新浪财经\n新浪个股资讯",
    "category": "量化",
    "impact_level": null,
    "id": "d68f5e01"
  },
  {
    "stock_code": "301308",
    "date": "2026-03-31 19:08",
    "title": "江波龙：投资者建议更名，董秘称现有名称利于业务发展",
    "content": "但贵司的名字叫 江波龙 ，我一度以为是水产行业。",
    "source": "新浪财经\n新浪个股资讯",
    "category": "事实",
    "impact_level": null,
    "id": "7067770c"
  },
  {
    "stock_code": "301308",
    "date": "2026-03-31 19:08",
    "title": "江波龙：投资者建议更名，董秘称现有名称利于业务发展",
    "content": "董秘你好，我也是听朋友说的，才知道贵司也是做存储芯片的。",
    "source": "新浪财经\n新浪个股资讯",
    "category": "事实",
    "impact_level": null,
    "id": "b6843ad5"
  },
  {
    "stock_code": "301308",
    "date": "2026-03-31 11:48",
    "title": "超3600股下跌\n半导体板块短线走低，扬杰科技跌超7%，佰维存储、德明利、江波龙、金海通等跟跌。",
    "content": "半导体板块短线走低，扬杰科技跌超7%，佰维存储、德明利、江波龙、金海通等跟跌。",
    "source": "新浪财经\n新浪个股资讯",
    "category": "量化",
    "impact_level": null,
    "id": "a9cb0b47"
  },
  {
    "stock_code": "301308",
    "date": "2026-03-31 11:48",
    "title": "超3600股下跌",
    "content": "盘面上，CPO、存储器、锂电池、半导体、光伏、AI算力、风电概念股走弱；",
    "source": "新浪财经\n新浪个股资讯",
    "category": "叙事",
    "impact_level": null,
    "id": "44e6f28e"
  },
  {
    "stock_code": "301308",
    "date": "2026-03-31 11:48",
    "title": "超3600股下跌",
    "content": "盘面上，CPO、锂电池、半导体、算力租赁、AI算力、光伏题材尽数回调，煤炭、化工、有色金属、电力行业跌幅靠前；",
    "source": "新浪财经\n新浪个股资讯",
    "category": "叙事",
    "impact_level": null,
    "id": "fe540afd"
  },
  {
    "stock_code": "301308",
    "date": "2026-03-31 09:36",
    "title": "半导体板块短线走低，扬杰科技跌超7%，佰维存储、德明利、江波龙、金海通等跟跌。",
    "content": "半导体板块短线走低，扬杰科技跌超7%，佰维存储、德明利、江波_7x24小时财经新闻_新浪网",
    "source": "新浪财经\n新浪个股资讯",
    "category": "量化",
    "impact_level": null,
    "id": "7399712f"
  },
  {
    "stock_code": "301308",
    "date": "2026-03-31 08:38",
    "title": "江波龙：定增事宜持续推进，预计2026年4月披露2025年年报",
    "content": "董秘你好，请问公司之前发布的定增事宜进展如何？",
    "source": "新浪财经\n新浪个股资讯",
    "category": "事实",
    "impact_level": null,
    "id": "67ddd76a"
  },
  {
    "stock_code": "301308",
    "date": "2026-03-31 08:38",
    "title": "江波龙：定增事宜持续推进，预计2026年4月披露2025年年报",
    "content": "公司生产经营正常，预计于2026年4月28日披露2025年年报，并随后或同时积极安排披露2026年一季报。",
    "source": "新浪财经\n新浪个股资讯",
    "category": "量化",
    "impact_level": null,
    "id": "e79bb1ae"
  },
  {
    "stock_code": "301308",
    "date": "2026-03-30 21:45",
    "title": "江波龙：公司已与包括长江存储在内的多家国内国际晶圆原厂建立了长期、稳定且深度的战略合作关系",
    "content": "公司将依托与原厂的深度合作优势，综合考量市场供需格局、客户需求等因素，择机推进兼顾短期成本效益与长期战略价值的采购合作安排。",
    "source": "新浪财经\n新浪个股资讯",
    "category": "事实",
    "impact_level": null,
    "id": "668847bb"
  },
  {
    "stock_code": "301308",
    "date": "2026-03-30 21:45",
    "title": "江波龙：公司已与包括长江存储在内的多家国内国际晶圆原厂建立了长期、稳定且深度的战略合作关系",
    "content": "证券日报网3月30日讯 ，江波龙在接受调研者提问时表示，公司已与包括长江存储、长鑫存储在内的多家国内国际晶圆原厂建立了长期、稳定且深度的战略合作关系。",
    "source": "新浪财经\n新浪个股资讯",
    "category": "量化",
    "impact_level": null,
    "id": "74623bc8"
  },
  {
    "stock_code": "301308",
    "date": "2026-03-30 21:45",
    "title": "江波龙：公司已与包括长江存储在内的多家国内国际晶圆原厂建立了长期、稳定且深度的战略合作关系",
    "content": "基于已落地的供应协议安排（长期供货协议等）及高效的库存管理机制，公司当前晶圆保障能力不仅能够有力支撑业务的稳定运行，也能充分满足公司向AI服务器、AI端侧等领域拓展的战略需求，供应链整体具备高度的稳定性与韧性。",
    "source": "新浪财经\n新浪个股资讯",
    "category": "事实",
    "impact_level": null,
    "id": "8b6558ce"
  },
  {
    "stock_code": "301308",
    "date": "2026-03-30 21:45",
    "title": "江波龙：OpenClaw等新型AI应用向端侧落地，将大幅提升终端设备的智能化水平",
    "content": "mSSD产品已获得众多头部PC厂商的高度认可，公司正着力推动mSSD成为AI端侧领域的新一代产品标准，进一步巩固并拓展在AI端侧市场的领先地位。",
    "source": "新浪财经\n新浪个股资讯",
    "category": "事实",
    "impact_level": null,
    "id": "9cf01ad5"
  },
  {
    "stock_code": "301308",
    "date": "2026-03-30 21:45",
    "title": "江波龙：OpenClaw等新型AI应用向端侧落地，将大幅提升终端设备的智能化水平",
    "content": "公司已推出了采用自主高难度系统级封装（SiP）技术的mSSD产品，性能满足PCIe的高标准，功耗满足NVMe协议的低功耗要求，并具备明显的物理特性与综合成本优势。",
    "source": "新浪财经\n新浪个股资讯",
    "category": "事实",
    "impact_level": null,
    "id": "5350fb18"
  },
  {
    "stock_code": "301308",
    "date": "2026-03-30 21:45",
    "title": "江波龙：OpenClaw等新型AI应用向端侧落地，将大幅提升终端设备的智能化水平",
    "content": "公司已推出UFS4.1、超薄ePOP5x、超薄ePOP4x、超小尺寸eMMC等新型嵌入式产品。",
    "source": "新浪财经\n新浪个股资讯",
    "category": "事实",
    "impact_level": null,
    "id": "83bfe937"
  },
  {
    "stock_code": "301308",
    "date": "2026-03-30 21:45",
    "title": "江波龙：OpenClaw等新型AI应用向端侧落地，将大幅提升终端设备的智能化水平",
    "content": "证券日报网3月30日讯 ，江波龙在接受调研者提问时表示，OpenClaw等新型AI应用向端侧落地，将大幅提升终端设备的智能化水平。",
    "source": "新浪财经\n新浪个股资讯",
    "category": "量化",
    "impact_level": null,
    "id": "bf5ffc96"
  },
  {
    "stock_code": "301308",
    "date": "2026-03-30 21:45",
    "title": "江波龙：OpenClaw等新型AI应用向端侧落地，将大幅提升终端设备的智能化水平",
    "content": "基于公司技术与产品优势，UFS4.1已进入多家全球知名智能手机厂商的供应链体系中，将在2026年实现规模化商业应用；",
    "source": "新浪财经\n新浪个股资讯",
    "category": "量化",
    "impact_level": null,
    "id": "3fa122c2"
  },
  {
    "stock_code": "301308",
    "date": "2026-03-30 21:45",
    "title": "江波龙：OpenClaw等新型AI应用向端侧落地，将大幅提升终端设备的智能化水平",
    "content": "为支持本地化大模型加载、实时数据处理等高负载任务功能，AI端侧设备需配备更大容量、更高带宽、更低延迟的存储产品，高性能的旗舰存储产品（UFS4.1、PCIe 5.0 SSD等）有望成为AI终端的主流配置，并成为驱动AI时代存储产业发展的核心动力之一。",
    "source": "新浪财经\n新浪个股资讯",
    "category": "影响",
    "impact_level": null,
    "id": "51d7c5db"
  },
  {
    "stock_code": "301308",
    "date": "2026-03-30 21:31",
    "title": "存储价格突然“跳水”引热议：回调信号还是短期波动？",
    "content": "江波龙 副总裁、嵌入式存储事业部总经理黄强日前对记者分析称，这类技术从长期来看是利好，有助于优化AI存储架构，缓解此前供需矛盾过于激烈的局面，从而推动行业更健康发展。",
    "source": "新浪财经\n新浪个股资讯",
    "category": "量化",
    "impact_level": null,
    "id": "688a9c46"
  },
  {
    "stock_code": "301308",
    "date": "2026-03-30 21:31",
    "title": "存储价格突然“跳水”引热议：回调信号还是短期波动？\n存储价格突然“跳水”：到底是回调信号，还是短期波动？",
    "content": "比如在嵌入式端，江波龙与紫光展锐联合开发，搭载紫光展锐芯片平台实测，4GB DDR搭配HLC技术后，20款App启动响应时间为851ms（毫秒），接近6GB/8GB DDR正常配置水平，降低了终端DRAM容量需求、优化了BOM（物料清单）成本。",
    "source": "新浪财经\n新浪个股资讯",
    "category": "事实",
    "impact_level": null,
    "id": "b23b664e"
  },
  {
    "stock_code": "301308",
    "date": "2026-03-30 21:31",
    "title": "存储价格突然“跳水”引热议：回调信号还是短期波动？",
    "content": "当前，为应对存储涨价给下游带来的成本压力，江波龙还自研了HLC（High Level Cache，高级缓存技术）技术，可以在减少DRAM使用的同时，不影响用户体验。",
    "source": "新浪财经\n新浪个股资讯",
    "category": "事实",
    "impact_level": null,
    "id": "4c8a5337"
  },
  {
    "stock_code": "301308",
    "date": "2026-03-30 14:54",
    "title": "健康指数观察 | 如何应对和把握2026年存储芯片“超级周期”？",
    "content": "随着大模型从聊天对话走向多步骤执行应用，Token调用量激增，推理算力需求呈指数级增长，而算力的核心载体——AI服务器，对存储芯片的需求数量巨大，更对性能、带宽提出更高要求。",
    "source": "新浪财经\n新浪个股资讯",
    "category": "事实",
    "impact_level": null,
    "id": "47ee5eb3"
  },
  {
    "stock_code": "301308",
    "date": "2026-03-30 14:54",
    "title": "健康指数观察 | 如何应对和把握2026年存储芯片“超级周期”？",
    "content": "云计算领域，AI大模型带动云服务需求增长，阿里云、百度智能云等纷纷上调AI算力及存储产品价格，进一步放大了存储芯片的需求缺口。",
    "source": "新浪财经\n新浪个股资讯",
    "category": "传导",
    "impact_level": null,
    "id": "5b85f095"
  },
  {
    "stock_code": "301308",
    "date": "2026-03-30 14:54",
    "title": "健康指数观察 | 如何应对和把握2026年存储芯片“超级周期”？",
    "content": "随着大模型迭代、智能体应用落地，AI算力需求呈指数级攀升，对高性能存储芯片的刚性需求激增，彻底改变了行业供需格局。",
    "source": "新浪财经\n新浪个股资讯",
    "category": "事实",
    "impact_level": null,
    "id": "482b7f01"
  },
  {
    "stock_code": "301308",
    "date": "2026-03-30 14:54",
    "title": "健康指数观察 | 如何应对和把握2026年存储芯片“超级周期”？",
    "content": "一方面，存储芯片制造依赖的无尘室空间扩张缓慢，全球半导体级“洁净室”（Cleanroom）建设周期长且资源紧缺，产能爬坡受限，SK海力士就曾表示，无尘室扩张滞后导致供给增长无法匹配需求增长；",
    "source": "新浪财经\n新浪个股资讯",
    "category": "传导",
    "impact_level": null,
    "id": "2a79cb47"
  },
  {
    "stock_code": "301308",
    "date": "2026-03-30 14:54",
    "title": "健康指数观察 | 如何应对和把握2026年存储芯片“超级周期”？",
    "content": "截至2026年3月，存储芯片行业已正式进入超级景气周期，成为半导体产业的第一增长极，2026年全球存储产值预计将突破5500亿美元，首次超过晶圆代工规模。",
    "source": "新浪财经\n新浪个股资讯",
    "category": "量化",
    "impact_level": null,
    "id": "e3ec3e02"
  },
  {
    "stock_code": "301308",
    "date": "2026-03-30 14:18",
    "title": "江波龙将mSSD扩展至PCIe Gen5，推出SPU存储处理单元",
    "content": "在锐龙 AI Max+ 395 硬件平台上，江波龙与 AMD 合作实现 397B 超大模型本地部署，在 256K 超长上下文（122B）场景下， 将 DRAM 占用降低近 40% 。",
    "source": "新浪财经\n新浪个股资讯",
    "category": "量化",
    "impact_level": null,
    "id": "6a01a3b1"
  },
  {
    "stock_code": "301308",
    "date": "2026-03-30 14:18",
    "title": "江波龙将mSSD扩展至PCIe Gen5，推出SPU存储处理单元",
    "content": "江波龙此次还推出了 SPU 和与其配套的 iSA 存储智能体。",
    "source": "新浪财经\n新浪个股资讯",
    "category": "事实",
    "impact_level": null,
    "id": "02615734"
  },
  {
    "stock_code": "301308",
    "date": "2026-03-30 14:18",
    "title": "江波龙将mSSD扩展至PCIe Gen5，推出SPU存储处理单元",
    "content": "针对 Gen5 mSSD 高热密度的属性，江波龙为其提供了集成均热板的散热解决方案。",
    "source": "新浪财经\n新浪个股资讯",
    "category": "事实",
    "impact_level": null,
    "id": "7d0e2965"
  },
  {
    "stock_code": "301308",
    "date": "2026-03-30 14:18",
    "title": "江波龙将mSSD扩展至PCIe Gen5，推出SPU存储处理单元",
    "content": "IT之家 3 月 30 日消息，江波龙 Longsys 在上周举行的 CFMS | MemoryS 2026 上宣布将其采用集成封装的 mSSD (Micro SSD) 产品线扩展至 PCIe Gen5，相较原有的 Gen4 解决方案实现显著性能提升。",
    "source": "新浪财经\n新浪个股资讯",
    "category": "量化",
    "impact_level": null,
    "id": "43eaa88f"
  },
  {
    "stock_code": "301308",
    "date": "2026-03-30 14:18",
    "title": "江波龙将mSSD扩展至PCIe Gen5，推出SPU存储处理单元",
    "content": "是面向智能存储架构打造的专用处理单元，这款代号 WM8500 的芯片采用 5nm 先进制程工艺， 可以 DRAM-less 实现 128TB 大容量 ，此外其支持 HLC 高级缓存和存内无损压缩技术，拥有 2:1 的平均压缩比。",
    "source": "新浪财经\n新浪个股资讯",
    "category": "事实",
    "impact_level": null,
    "id": "669a26c2"
  },
  {
    "stock_code": "301308",
    "date": "2026-03-30 14:18",
    "title": "江波龙将mSSD扩展至PCIe Gen5，推出SPU存储处理单元",
    "content": "而 iSA 存储智能体是面向端侧 AI 推理的智能调度引擎，可高效解决端侧 AI 推理的存储调度难题。",
    "source": "新浪财经\n新浪个股资讯",
    "category": "事实",
    "impact_level": null,
    "id": "2062c8e9"
  },
  {
    "stock_code": "301308",
    "date": "2026-03-30 11:17",
    "title": "车规存储的“结构性缺口”如何填补？",
    "content": "在近日举办的MemoryS 2026峰会上，江波龙进一步提出“端侧AI集成存储”的战略方向，明确将智能汽车作为端侧AI的核心落地场景之一，其端侧AI存储Foundry模式覆盖芯片设计、封装工艺、材料工程等全产业链环节，为高阶辅助驾驶等车载AI场景提供定制化存储支撑。",
    "source": "新浪财经\n新浪个股资讯",
    "category": "量化",
    "impact_level": null,
    "id": "b7d6035c"
  },
  {
    "stock_code": "301308",
    "date": "2026-03-30 11:17",
    "title": "车规存储的“结构性缺口”如何填补？",
    "content": "作为国内较早布局车规存储的厂商，江波龙在七年前便将汽车存储确立为重点方向，逐步构建起一套以商业模式创新为牵引、以主控芯片设计、固件算法开发到高端封测制造的全链条能力为支撑的解决方案。",
    "source": "新浪财经\n新浪个股资讯",
    "category": "量化",
    "impact_level": null,
    "id": "c66ac9b9"
  },
  {
    "stock_code": "301308",
    "date": "2026-03-30 11:17",
    "title": "车规存储的“结构性缺口”如何填补？",
    "content": "TCM模式（存储技术合约制造）是江波龙于2024年首次公开提出，核心价值在于打通晶圆厂与车企的供需链路。",
    "source": "新浪财经\n新浪个股资讯",
    "category": "量化",
    "impact_level": null,
    "id": "cbfe79b0"
  },
  {
    "stock_code": "301308",
    "date": "2026-03-30 09:53",
    "title": "中信证券：AI推理带动存储需求爆发 持续看好存储创新成长趋势",
    "content": "在端侧运行百亿或千亿参数大模型对内存是巨大考验，江波龙推出搭载5nm SPU的存储处理单元与iSA存储智能体，在联合调优验证中在PC主机上实现397B模型本地部署，并在256K上下文场景下降低近40%的DRAM占用;",
    "source": "新浪财经\n新浪个股资讯",
    "category": "量化",
    "impact_level": null,
    "id": "644fb541"
  },
  {
    "stock_code": "301308",
    "date": "2026-03-30 09:53",
    "title": "中信证券：AI推理带动存储需求爆发 持续看好存储创新成长趋势",
    "content": "江波龙则推动HLC高级缓存技术在嵌入式端落地，以降低终端BOM成本。",
    "source": "新浪财经\n新浪个股资讯",
    "category": "事实",
    "impact_level": null,
    "id": "4d3ac60a"
  },
  {
    "stock_code": "301308",
    "date": "2026-03-30 09:53",
    "title": "中信证券：AI推理带动存储需求爆发 持续看好存储创新成长趋势",
    "content": "目前，受制于存储带宽瓶颈，GPU集群的可用度(利用率)仅约46%至50%。",
    "source": "新浪财经\n新浪个股资讯",
    "category": "量化",
    "impact_level": null,
    "id": "550b9193"
  },
  {
    "stock_code": "301308",
    "date": "2026-03-27 21:16",
    "title": "江波龙：在AI端侧领域，已推出mSSD、UFS 4.1等高端存储产品",
    "content": "向 江波龙 （301308.SZ） 提问，近期谷歌发布的TurboQuant无损向量量化技术，引发了行业对AI推理效率与存储需求变化的广泛关注，市场普遍认为该技术有望大幅降低长上下文大模型的部署门槛，加速端侧AI、企业级AI应用的规模化普及。",
    "source": "新浪财经\n新浪个股资讯",
    "category": "影响",
    "impact_level": null,
    "id": "610fea3d"
  },
  {
    "stock_code": "301308",
    "date": "2026-03-27 21:16",
    "title": "江波龙：在AI端侧领域，已推出mSSD、UFS 4.1等高端存储产品\n江波龙：回应无损向量量化技术影响及端侧AI存储产品进展\n江波龙：回应谷歌新技术影响，展示多领域存储技术储备与布局",
    "content": "在存储主控芯片及固件领域，公司已经发布多款自控主控芯片并批量部署，未来公司将继续依托自研主控芯片技术、自有封测平台，不断推出适合时代发展需要的各类存储产品。",
    "source": "新浪财经\n新浪个股资讯",
    "category": "量化",
    "impact_level": null,
    "id": "61ed9593"
  },
  {
    "stock_code": "301308",
    "date": "2026-03-27 21:16",
    "title": "江波龙：在AI端侧领域，已推出mSSD、UFS 4.1等高端存储产品\n江波龙：介绍企业级存储产品应用场景及客户覆盖情况\n江波龙：回应谷歌新技术影响，展示多领域存储技术储备与布局",
    "content": "公司是国内少数具备“eSSD+RDIMM”产品设计、组合以及规模供应能力的企业，并前沿布局了以SOCAMM2为代表的多款新一代高性能存储产品。",
    "source": "新浪财经\n新浪个股资讯",
    "category": "事实",
    "impact_level": null,
    "id": "01efff99"
  },
  {
    "stock_code": "301308",
    "date": "2026-03-27 21:16",
    "title": "江波龙：在AI端侧领域，已推出mSSD、UFS 4.1等高端存储产品\n江波龙：回应无损向量量化技术影响及端侧AI存储产品进展\n江波龙：回应谷歌新技术影响，展示多领域存储技术储备与布局",
    "content": "在AI端侧领域，公司已推出mSSD、UFS 4.1、超薄ePOP5x、超薄ePOP4x、超小尺寸eMMC等高端存储产品，适配AI端侧对存储的高性能、高集成度要求。",
    "source": "新浪财经\n新浪个股资讯",
    "category": "事实",
    "impact_level": null,
    "id": "95ac0d40"
  },
  {
    "stock_code": "301308",
    "date": "2026-03-27 21:16",
    "title": "江波龙：在AI端侧领域，已推出mSSD、UFS 4.1等高端存储产品\n江波龙：回应谷歌新技术影响，展示多领域存储技术储备与布局",
    "content": "针对AI大模型推理、向量检索等相关场景，公司在端侧AI存储、AI优化型企业级SSD、存储主控与固件自研等领域，有哪些已落地的技术储备和客户布局？",
    "source": "新浪财经\n新浪个股资讯",
    "category": "事实",
    "impact_level": null,
    "id": "9b63e7c7"
  },
  {
    "stock_code": "301308",
    "date": "2026-03-27 21:16",
    "title": "江波龙：在AI端侧领域，已推出mSSD、UFS 4.1等高端存储产品\n江波龙：回应谷歌新技术影响，展示多领域存储技术储备与布局",
    "content": "根据媒体公开报道，该技术尚在推出初期，公司将持续关注。",
    "source": "新浪财经\n新浪个股资讯",
    "category": "量化",
    "impact_level": null,
    "id": "13c06c84"
  },
  {
    "stock_code": "301308",
    "date": "2026-03-27 21:02",
    "title": "千元机时代终结，旧手机更值钱：存储涨价的另一面",
    "content": "过去一年的涨价潮直接拉高了江波龙的利润，公司2025年业绩预告显示，江波龙的净利润比上一年同期预计增长150%到210%，达到12.5亿元到15.5亿元。",
    "source": "新浪财经\n新浪个股资讯",
    "category": "量化",
    "impact_level": null,
    "id": "9ac176cc"
  },
  {
    "stock_code": "301308",
    "date": "2026-03-27 21:02",
    "title": "千元机时代终结，旧手机更值钱：存储涨价的另一面",
    "content": "2025年末的一次机构调研中，在被问及“存储价格上涨将如何影响公司的利润水平”时，江波龙方面表示，晶圆采购至存储器销售的生产周期间隔，决定了存储晶圆价格上行时对公司毛利率将产生正面影响。",
    "source": "新浪财经\n新浪个股资讯",
    "category": "量化",
    "impact_level": null,
    "id": "c96db6a1"
  },
  {
    "stock_code": "301308",
    "date": "2026-03-27 21:02",
    "title": "千元机时代终结，旧手机更值钱：存储涨价的另一面",
    "content": "Wind数据显示，2025年一季度开始，江波龙开始有意识提升自己的存货：其一、二、三季度存货分别为78.14亿元、80.76亿元、85.17亿元。",
    "source": "新浪财经\n新浪个股资讯",
    "category": "量化",
    "impact_level": null,
    "id": "ff46613f"
  },
  {
    "stock_code": "301308",
    "date": "2026-03-27 21:02",
    "title": "千元机时代终结，旧手机更值钱：存储涨价的另一面",
    "content": "内存涨价让国产NAND模组龙头江波龙一年间股价大涨。",
    "source": "新浪财经\n新浪个股资讯",
    "category": "量化",
    "impact_level": null,
    "id": "4e6c9385"
  },
  {
    "stock_code": "301308",
    "date": "2026-03-27 21:02",
    "title": "千元机时代终结，旧手机更值钱：存储涨价的另一面",
    "content": "包括三星电子、SK海力士、美光在内的诸多存储厂商都将稀缺的先进制程产能优先分配给服务于AI且利润更高、技术壁垒更强的高带宽内存（HBM）和高端服务器DRAM（如DDR5）。",
    "source": "新浪财经\n新浪个股资讯",
    "category": "事实",
    "impact_level": null,
    "id": "26232201"
  },
  {
    "stock_code": "301308",
    "date": "2026-03-27 20:45",
    "title": "江波龙：介绍企业级存储产品应用场景及客户覆盖情况",
    "content": "公司此前已公开企业级SSD业务实现高速增长￼￼￼，请问公司的企业级存储产品，针对AI推理、向量数据库等场景做了哪些适配优化？",
    "source": "新浪财经\n新浪个股资讯",
    "category": "事实",
    "impact_level": null,
    "id": "a67e66ff"
  },
  {
    "stock_code": "301308",
    "date": "2026-03-27 20:45",
    "title": "江波龙：回应无损向量量化技术影响及端侧AI存储产品进展",
    "content": "公司作为国内嵌入式存储龙头，此前已公开定制化端侧AI存储产品在头部客户处批量出货￼￼￼，请问公司的UFS、mSSD等核心产品，针对AI大模型场景做了哪些专属的主控与固件优化？",
    "source": "新浪财经\n新浪个股资讯",
    "category": "量化",
    "impact_level": null,
    "id": "6cef8c6a"
  },
  {
    "stock_code": "301308",
    "date": "2026-03-27 20:45",
    "title": "江波龙：回应无损向量量化技术影响及端侧AI存储产品进展",
    "content": "董秘您好，近期行业内无损向量量化技术的迭代，被认为将大幅降低端侧大模型长上下文推理的硬件门槛，进一步打开端侧AI的应用空间。",
    "source": "新浪财经\n新浪个股资讯",
    "category": "事实",
    "impact_level": null,
    "id": "198ead2b"
  },
  {
    "stock_code": "301308",
    "date": "2026-03-27 20:45",
    "title": "江波龙：回应无损向量量化技术影响及端侧AI存储产品进展",
    "content": "目前在端侧AI领域的客户落地和规模化应用进展如何？",
    "source": "新浪财经\n新浪个股资讯",
    "category": "事实",
    "impact_level": null,
    "id": "e97b4fe6"
  },
  {
    "stock_code": "301308",
    "date": "2026-03-27 20:45",
    "title": "江波龙：介绍企业级存储产品应用场景及客户覆盖情况",
    "content": "目前在相关领域的客户认证和订单落地情况如何？",
    "source": "新浪财经\n新浪个股资讯",
    "category": "事实",
    "impact_level": null,
    "id": "c0c2ed7d"
  },
  {
    "stock_code": "301308",
    "date": "2026-03-27 20:45",
    "title": "江波龙：回应无损向量量化技术影响及端侧AI存储产品进展",
    "content": "根据媒体公开报道，该技术尚在推出初期，公司将持续关注影响。",
    "source": "新浪财经\n新浪个股资讯",
    "category": "事实",
    "impact_level": null,
    "id": "9fba6b31"
  },
  {
    "stock_code": "301308",
    "date": "2026-03-27 20:45",
    "title": "江波龙：回应谷歌新技术影响，展示多领域存储技术储备与布局",
    "content": "请问公司如何看待该技术带来的存储行业需求结构变化？",
    "source": "新浪财经\n新浪个股资讯",
    "category": "事实",
    "impact_level": null,
    "id": "ac78a3d9"
  },
  {
    "stock_code": "301308",
    "date": "2026-03-27 20:45",
    "title": "江波龙：介绍企业级存储产品应用场景及客户覆盖情况",
    "content": "董秘您好，近期行业内向量量化技术的迭代，被认为将推动企业级AI推理、向量检索系统的规模化下沉，带来企业级存储的新增需求。",
    "source": "新浪财经\n新浪个股资讯",
    "category": "事实",
    "impact_level": null,
    "id": "1d9df65c"
  },
  {
    "stock_code": "301308",
    "date": "2026-03-27 20:45",
    "title": "江波龙：介绍企业级存储产品应用场景及客户覆盖情况",
    "content": "公司企业级产品面向HPC、通用服务器、AI集群服务器、AI训练/推理、智能辅助驾驶和工业边缘网关等应用场景，客户涵盖互联网企业、运营商、服务器厂商等。",
    "source": "新浪财经\n新浪个股资讯",
    "category": "事实",
    "impact_level": null,
    "id": "42f9dcc1"
  },
  {
    "stock_code": "301308",
    "date": "2026-03-27 20:14",
    "title": "江波龙：公司对外担保总额度为人民币150.55亿元",
    "content": "证券日报网讯 3月27日，江波龙发布公告称，截至本公告披露日，本次提供担保后，公司对外担保总额度为人民币150.55亿元，占公司最近一期经审计净资产的比例为232.80%。",
    "source": "新浪财经\n新浪个股资讯",
    "category": "量化",
    "impact_level": null,
    "id": "cc419756"
  },
  {
    "stock_code": "301308",
    "date": "2026-03-27 20:08",
    "title": "江波龙：目前存储行业处于高景气周期",
    "content": "依据相关规定，互动易并非公司信息披露的法定平台，为公平对待全体投资人，请以公司相关定期报告披露的数据为准。",
    "source": "新浪财经\n新浪个股资讯",
    "category": "事实",
    "impact_level": null,
    "id": "0d80be4b"
  },
  {
    "stock_code": "301308",
    "date": "2026-03-27 20:08",
    "title": "江波龙：目前存储行业处于高景气周期",
    "content": "证券日报网讯3月27日， 江波龙 在互动平台回答投资者提问时表示，从行业来看，受AI需求拉动以及存储晶圆原厂 资本开支 谨慎及投入存在结构性差异的影响，目前存储行业处于高景气 周期 ，可以通过查阅公司公布的相关投资者关系活动记录表或者第三方信息了解更多。",
    "source": "新浪财经\n新浪个股资讯",
    "category": "量化",
    "impact_level": null,
    "id": "6f803d5c"
  },
  {
    "stock_code": "301308",
    "date": "2026-03-27 16:57",
    "title": "单季净利增1105%，这家存储厂还在猛踩油门",
    "content": "同期，佰维存储的净利润同比激增429.07%，江波龙预告的净利润增长区间也在150.66%-210.82%。",
    "source": "新浪财经\n新浪个股资讯",
    "category": "量化",
    "impact_level": null,
    "id": "ec989795"
  },
  {
    "stock_code": "301308",
    "date": "2026-03-27 16:57",
    "title": "单季净利增1105%，这家存储厂还在猛踩油门",
    "content": "相比之下，江波龙与佰维存储则一直有大容量SSD矩阵，过去积极的存货也让这两家的利润释放更为迅速。",
    "source": "新浪财经\n新浪个股资讯",
    "category": "事实",
    "impact_level": null,
    "id": "589bf882"
  },
  {
    "stock_code": "301308",
    "date": "2026-03-27 16:57",
    "title": "单季净利增1105%，这家存储厂还在猛踩油门",
    "content": "而江波龙与佰维存储这一数字分别为43.67%和43.17%。",
    "source": "新浪财经\n新浪个股资讯",
    "category": "量化",
    "impact_level": null,
    "id": "a1d7cbd4"
  },
  {
    "stock_code": "301308",
    "date": "2026-03-27 16:57",
    "title": "单季净利增1105%，这家存储厂还在猛踩油门",
    "content": "相比之下，江波龙和佰维存储2025年前三季度末存货跌价准备计提比例分别为1.75%、5.05%。",
    "source": "新浪财经\n新浪个股资讯",
    "category": "量化",
    "impact_level": null,
    "id": "0b29050a"
  },
  {
    "stock_code": "301308",
    "date": "2026-03-27 16:57",
    "title": "单季净利增1105%，这家存储厂还在猛踩油门",
    "content": "本轮存储产品价格普涨，原因很简单，AI发展下算力飙升带动内存需求增长，而美光、三星和SK海力士等海外大厂，将DDR4产能转投DDR5和HBM，中低端产能缩减，相关产品价格由此攀升。",
    "source": "新浪财经\n新浪个股资讯",
    "category": "传导",
    "impact_level": null,
    "id": "6de2902e"
  },
  {
    "stock_code": "301308",
    "date": "2026-03-27 16:18",
    "title": "江波龙：公司近期的董事以及高级管理人员减持主要系公司股东个人资金需求安排",
    "content": "公司按照上市规则及相关规范的要求，提前进行公告，减持数量亦严格遵循可减持数量的相关限制。",
    "source": "新浪财经\n新浪个股资讯",
    "category": "事实",
    "impact_level": null,
    "id": "24e1d88b"
  },
  {
    "stock_code": "301308",
    "date": "2026-03-27 16:18",
    "title": "江波龙：公司近期的董事以及高级管理人员减持主要系公司股东个人资金需求安排",
    "content": "与此同时，公司实控人自上市以来，尚未进行任何形式的减持。",
    "source": "新浪财经\n新浪个股资讯",
    "category": "事实",
    "impact_level": null,
    "id": "41db3593"
  },
  {
    "stock_code": "301308",
    "date": "2026-03-27 16:18",
    "title": "江波龙：公司近期的董事以及高级管理人员减持主要系公司股东个人资金需求安排",
    "content": "最后，从行业来看，受AI需求拉动以及存储晶圆原厂资本开支谨慎及投入存在结构性差异的影响，目前存储行业处于高景气周期，可以通过查阅公司公布的相关投资者关系活动记录表或者第三方信息了解更多。",
    "source": "新浪财经\n新浪个股资讯",
    "category": "事实",
    "impact_level": null,
    "id": "a293541b"
  },
  {
    "stock_code": "301308",
    "date": "2026-03-27 16:18",
    "title": "江波龙：公司近期的董事以及高级管理人员减持主要系公司股东个人资金需求安排",
    "content": "最后，公司作为行业领先企业，目前生产经营正常，正在积极把握行业的历史性机遇，依托自研存储芯片、自研主控芯片、自有封测平台等核心技术优势，继续保持行业以及资本市场的领先优势。",
    "source": "新浪财经\n新浪个股资讯",
    "category": "事实",
    "impact_level": null,
    "id": "5a11b8c3"
  },
  {
    "stock_code": "301308",
    "date": "2026-03-27 16:18",
    "title": "江波龙：公司近期的董事以及高级管理人员减持主要系公司股东个人资金需求安排",
    "content": "证券日报网讯 3月27日，江波龙在互动平台回答投资者提问时表示，公司近期的董事以及高级管理人员减持，主要系公司股东个人资金需求安排，与公司生产经营情况无关。",
    "source": "新浪财经\n新浪个股资讯",
    "category": "量化",
    "impact_level": null,
    "id": "2a15ca11"
  },
  {
    "stock_code": "301308",
    "date": "2026-03-27 14:03",
    "title": "V观财报丨江波龙：公司目前未和英伟达有直接合作",
    "content": "【V观财报丨江波龙：公司目前未和英伟达有直接合作】江波龙3月27日在投资者互动平台回复提问表示，公司目前未和英伟达有直接合作，公司围绕AI大模型应用场景，推出了SATA SSD、PCIe SSD、RDIMM等企业级存储产品，并发布了MRDIMM、CXL2.0内存拓展模块、SOCAMM2等多款前沿高性能存储产品，客户涵盖运营商、互联网企业、服务器厂商等。",
    "source": "新浪财经\n新浪个股资讯",
    "category": "量化",
    "impact_level": null,
    "id": "31a67705"
  },
  {
    "stock_code": "301308",
    "date": "2026-03-27 11:48",
    "title": "江波龙：公司目前未和英伟达有直接合作",
    "content": "江波龙3月27日在互动平台表示， 公司目前未和英伟达有直接合作，公司围绕AI大模型应用场景，推出了SATA SSD、PCIe SSD、RDIMM等企业级存储产品，并发布了MRDIMM、CXL2.0内存拓展模块、SOCAMM2等多款前沿高性能存储产品，客户涵盖运营商、互联网企业、服务器厂商等。",
    "source": "新浪财经\n新浪个股资讯",
    "category": "量化",
    "impact_level": null,
    "id": "b1e92197"
  },
  {
    "stock_code": "301308",
    "date": "2026-03-27 11:45",
    "title": "投资者提问：近期A股市场情绪波动较大，沪指跌破4000点，投资者对地缘冲突...",
    "content": "在这样的市场环境下， 江波龙 作为存储龙头，如何通过更有效的叙事让投资者理解公司在＇AI存储需求爆发＇与公司的前景，是否考虑过用更具体、更数据化的方式（如分业务板块的毛利率变化、AI相关产品的收入占比等）来替代笼统的＇生产经营正常＇式回应，从而增强投资者对公司的信任度？",
    "source": "新浪财经\n新浪个股资讯",
    "category": "传导",
    "impact_level": null,
    "id": "b45f7784"
  },
  {
    "stock_code": "301308",
    "date": "2026-03-24 18:26",
    "title": "关于为子公司向银行申请并购贷款提供担保的公告",
    "content": "（二）《权利最高额质押合同》的主要内容1、质权人（债权人）：上海浦东发展银行股份有限公司上海自贸试验区新片区分行2、出质人：上海江波龙存储技术有限公司3、债务人：上海慧忆半导体有限公司4、质押财产：上海江波龙存储持有的慧忆半导体100%股权",
    "source": "巨潮资讯\n巨潮资讯公告",
    "category": "量化",
    "impact_level": null,
    "id": "7175ff50"
  },
  {
    "stock_code": "301308",
    "date": "2026-03-24 18:26",
    "title": "关于为子公司向银行申请并购贷款提供担保的公告",
    "content": "（一）《最高额保证合同》的主要内容1、债权人：上海浦东发展银行股份有限公司上海自贸试验区新片区分行2、保证人：深圳市江波龙电子股份有限公司3、债务人：上海慧忆半导体有限公司4、保证方式：连带责任保证保证人确认，当债务人未按主合同约定履行其债务时，无论债权人对主合同项下的债权是否拥有其他担保权利(包括但不限于保证、抵押、质押等担保方式)，",
    "source": "巨潮资讯\n巨潮资讯公告",
    "category": "量化",
    "impact_level": null,
    "id": "d067ccdd"
  },
  {
    "stock_code": "301308",
    "date": "2026-03-24 18:26",
    "title": "关于为子公司向银行申请并购贷款提供担保的公告",
    "content": "4、 上海江波龙存储与浦发银行签署的《权利最高额质押合同》；",
    "source": "巨潮资讯\n巨潮资讯公告",
    "category": "事实",
    "impact_level": null,
    "id": "0f7cbbe5"
  },
  {
    "stock_code": "301308",
    "date": "2026-03-24 18:26",
    "title": "关于为子公司向银行申请并购贷款提供担保的公告",
    "content": "公司全资子公司上海江波龙存储技术有限公司（以下简称“上海江波龙存储”）",
    "source": "巨潮资讯\n巨潮资讯公告",
    "category": "事实",
    "impact_level": null,
    "id": "acc7041a"
  },
  {
    "stock_code": "301308",
    "date": "2026-03-24 18:26",
    "title": "关于为子公司向银行申请并购贷款提供担保的公告",
    "content": "深圳市江波龙电子股份有限公司（以下简称“公司”）提供的担保总额超过公司最近一期经审计净资产的100%，其中对资产负债率超过70%的单位的担保总额超过公司最近一期经审计净资产50%，前述担保全部为公司对合并报表范围内子公司的担保，敬请投资者充分关注担保风险。",
    "source": "巨潮资讯\n巨潮资讯公告",
    "category": "量化",
    "impact_level": null,
    "id": "0b5bcb34"
  },
  {
    "stock_code": "301308",
    "date": "2026-03-24 18:26",
    "title": "关于为子公司向银行申请并购贷款提供担保的公告",
    "content": "单位：人民币亿元担保方被担保方担保方持股比例被担保方最近一期资产负债率经审批的预计担保额度担保额度占上市公司最近一期净资产比例是否关联担保公司慧忆半导体100%66.21%12.5019.33%否注：",
    "source": "巨潮资讯\n巨潮资讯公告",
    "category": "政策",
    "impact_level": null,
    "id": "4a3c8069"
  },
  {
    "stock_code": "301308",
    "date": "2026-03-23 19:06",
    "title": "2026年3月16日-19日投资者关系活动记录表",
    "content": "近期由江波龙主办、中国汽车工业协会指导的车规存储创新生态交流会在苏州成功举办，",
    "source": "巨潮资讯\n巨潮资讯公告",
    "category": "事实",
    "impact_level": null,
    "id": "6f4c32ea"
  },
  {
    "stock_code": "301308",
    "date": "2026-03-23 18:44",
    "title": "关于公司为子公司提供担保的进展公告",
    "content": "1、债权人：上海银行股份有限公司上海自贸试验区分行2、债务人：上海江波龙数字技术有限公司3、保证人：深圳市江波龙电子股份有限公司4、被担保的主合同项下最高主债权限额：人民币2亿元（贰亿元整）",
    "source": "巨潮资讯\n巨潮资讯公告",
    "category": "量化",
    "impact_level": null,
    "id": "63ba37e7"
  },
  {
    "stock_code": "301308",
    "date": "2026-03-23 18:44",
    "title": "关于公司为子公司提供担保的进展公告",
    "content": "1、债权人：中国进出口银行深圳分行2、债务人：江波龙电子（香港）有限公司3、保证人：深圳市江波龙电子股份有限公司4、被担保的主合同项下全部债务本金：人民币5亿元（伍亿元整）",
    "source": "巨潮资讯\n巨潮资讯公告",
    "category": "量化",
    "impact_level": null,
    "id": "07d328fc"
  },
  {
    "stock_code": "301308",
    "date": "2026-03-23 18:44",
    "title": "关于公司为子公司提供担保的进展公告",
    "content": "（二）关于为江波龙数字技术提供担保的进展情况因江波龙数字技术日常经营的需要，公司为江波龙数字技术向上海银行股份有限公司上海自贸试验区分行（以下简称“上海银行”）申请综合授信业务提供债权本金最高不超过人民币2亿元的最高额保证担保，并与上海银行签署了《最高额保证合同》。",
    "source": "巨潮资讯\n巨潮资讯公告",
    "category": "量化",
    "impact_level": null,
    "id": "d56aafb7"
  },
  {
    "stock_code": "301308",
    "date": "2026-03-23 18:44",
    "title": "关于公司为子公司提供担保的进展公告",
    "content": "（一）关于为香港江波龙提供担保的进展情况因香港江波龙日常经营的需要，香港江波龙与中国进出口银行深圳分行（以下简称“中国进出口银行”）签署了《借款合同》，香港江波龙向中国进出口银行借款人民币5亿元。",
    "source": "巨潮资讯\n巨潮资讯公告",
    "category": "量化",
    "impact_level": null,
    "id": "25421be8"
  },
  {
    "stock_code": "301308",
    "date": "2026-03-23 18:44",
    "title": "关于公司为子公司提供担保的进展公告",
    "content": "（二）江波龙数字技术：公司与上海银行签署的《最高额保证合同》",
    "source": "巨潮资讯\n巨潮资讯公告",
    "category": "事实",
    "impact_level": null,
    "id": "0962e1c7"
  },
  {
    "stock_code": "301308",
    "date": "2026-03-23 18:44",
    "title": "关于公司为子公司提供担保的进展公告",
    "content": "（一）香港江波龙：公司与中国进出口银行签署的《担保合同》",
    "source": "巨潮资讯\n巨潮资讯公告",
    "category": "事实",
    "impact_level": null,
    "id": "1bf3e296"
  },
  {
    "stock_code": "301308",
    "date": "2026-03-19 20:02",
    "title": "2026年第一次临时股东会决议公告",
    "content": "（一）深圳市江波龙电子股份有限公司2026年第一次临时股东会决议；",
    "source": "巨潮资讯\n巨潮资讯公告",
    "category": "量化",
    "impact_level": null,
    "id": "7a1465a7"
  },
  {
    "stock_code": "301308",
    "date": "2026-03-19 20:02",
    "title": "2026年第一次临时股东会决议公告",
    "content": "等有关法律、行政法规、部门规章、规范性文件和《深圳市江波龙电子股份有限公司章程》（以下简称“《公司章程》”）的有关规定。",
    "source": "巨潮资讯\n巨潮资讯公告",
    "category": "事实",
    "impact_level": null,
    "id": "b0919110"
  },
  {
    "stock_code": "301308",
    "date": "2026-03-19 19:24",
    "title": "关于董事、高级管理人员减持股份预披露公告",
    "content": "1、持有深圳市江波龙电子股份有限公司（以下简称“公司”）股份18,908,548股（占公司总股本比例为4.5112%）的公司董事李志雄先生，计划在2026年4月13日至2026年7月12日期间通过证券交易所以集中竞价、大宗交易方式合计减持公司股份不超过2,400,000股（占公司总股本比例为0.5726%）。",
    "source": "巨潮资讯\n巨潮资讯公告",
    "category": "量化",
    "impact_level": null,
    "id": "35612228"
  },
  {
    "stock_code": "301308",
    "date": "2026-03-19 19:24",
    "title": "关于董事、高级管理人员减持股份预披露公告",
    "content": "2、持有深圳市江波龙电子股份有限公司（以下简称“公司”）股份91,944股（占公司总股本比例为0.0219%）的公司副总经理高喜春先生，计划在2026年4月13日至2026年7月12日期间通过证券交易所以集中竞价、大宗交易方式合计减持公司股份不超过22,986股（占公司总股本比例为0.0055%）。",
    "source": "巨潮资讯\n巨潮资讯公告",
    "category": "量化",
    "impact_level": null,
    "id": "b440d323"
  },
  {
    "stock_code": "301308",
    "date": "2026-03-19 00:00",
    "title": "江波龙 最新资讯_ 江波龙 个人资料简介_ 江波龙 电子",
    "content": "中国存储企业江波龙凭借技术创新，率先推出LPCAMM2和SOCAMM2内存模块，实现容量密度提升50%、功耗降低30%，切入超薄笔记本和AI服务器市场。",
    "source": "站长之家\n搜狗检索补召回",
    "category": "量化",
    "impact_level": null,
    "id": "b995d3cc"
  },
  {
    "stock_code": "301308",
    "date": "2026-03-19 00:00",
    "title": "江波龙 最新资讯_ 江波龙 个人资料简介_ 江波龙 电子",
    "content": "江波龙凭借全栈技术能力，深耕半导体存储领域，推出覆盖eSSD、内存模块等产品矩阵，以“大容量、高性能、低功耗”满足AI行业需求。",
    "source": "站长之家\n搜狗检索补召回",
    "category": "事实",
    "impact_level": null,
    "id": "822ab59a"
  },
  {
    "stock_code": "301308",
    "date": "2026-03-19 00:00",
    "title": "江波龙 最新资讯_ 江波龙 个人资料简介_ 江波龙 电子",
    "content": "2025年，AI强劲拉动半导体存储行业全面增长与升级。",
    "source": "站长之家\n搜狗检索补召回",
    "category": "量化",
    "impact_level": null,
    "id": "8f1c79fa"
  },
  {
    "stock_code": "301308",
    "date": "2026-03-19 00:00",
    "title": "江波龙 最新资讯_ 江波龙 个人资料简介_ 江波龙 电子",
    "content": "江波龙凭借20余年技术积累，构建了覆盖AI全场景的企业级存储矩阵，从eSSD到创新内存方案，为AI智算中心提供高效可靠支持。",
    "source": "站长之家\n搜狗检索补召回",
    "category": "量化",
    "impact_level": null,
    "id": "d7a2c2c5"
  },
  {
    "stock_code": "301308",
    "date": "2026-03-19 00:00",
    "title": "江波龙 最新资讯_ 江波龙 个人资料简介_ 江波龙 电子",
    "content": "江波龙在会上发布基于LPDDR5/5x的创新企业级内存产品SOCAMM2，应对AI工作负载挑战；",
    "source": "站长之家\n搜狗检索补召回",
    "category": "事实",
    "impact_level": null,
    "id": "9a789727"
  },
  {
    "stock_code": "301308",
    "date": "2026-03-19 00:00",
    "title": "江波龙 最新资讯_ 江波龙 个人资料简介_ 江波龙 电子",
    "content": "中国半导体企业江波龙在智能汽车存储领域取得显著进展。",
    "source": "站长之家\n搜狗检索补召回",
    "category": "事实",
    "impact_level": null,
    "id": "50de4058"
  }
]